README.md
setup.py
aioyoutube/__init__.py
aioyoutube/api.py
aioyoutube.egg-info/PKG-INFO
aioyoutube.egg-info/SOURCES.txt
aioyoutube.egg-info/dependency_links.txt
aioyoutube.egg-info/requires.txt
aioyoutube.egg-info/top_level.txt
aioyoutube/exeptions/__init__.py
aioyoutube/exeptions/base.py
aioyoutube/exeptions/request.py
aioyoutube/exeptions/response.py
aioyoutube/handlers/__init__.py
aioyoutube/handlers/error.py
aioyoutube/handlers/validation.py
aioyoutube/helpers/__init__.py
aioyoutube/helpers/base.py