Metadata-Version: 2.1
Name: aioyoutube
Version: 0.1.6
Summary: Async wrapper for REST API youtube.com
Home-page: https://github.com/diarts/aioyoutube.git
Author: konstantin
Author-email: korobanov1993@yandex.ru
License: MIT
Platform: UNKNOWN
Classifier: Programming Language :: Python :: 3
Requires-Python: >=3.7.2
